README.md
firefox_profile.py
setup.py
firefox_profile.egg-info/PKG-INFO
firefox_profile.egg-info/SOURCES.txt
firefox_profile.egg-info/dependency_links.txt
firefox_profile.egg-info/entry_points.txt
firefox_profile.egg-info/requires.txt
firefox_profile.egg-info/top_level.txt