Metadata-Version: 2.1
Name: firefox-profile
Version: 0.0.3
Summary: Utility to access Firefox profile data.
Home-page: https://github.com/luismsgomes/firefox-profile
Author: Luís Gomes
Author-email: luismsgomes@gmail.com
License: MIT
Keywords: firefox util commandline
Platform: UNKNOWN
Classifier: Development Status :: 3 - Alpha
Classifier: License :: OSI Approved :: MIT License
Classifier: Programming Language :: Python :: 3.7
